git_templates/__init__.py
git_templates/commands/__init__.py
git_templates/commands/add.py
git_templates/commands/remove.py
git_templates/commands/update.py
git_templates/commands/utils.py
git_templates/main.py
git_templates-0.1.2.dist-info/METADATA
git_templates-0.1.2.dist-info/WHEEL
git_templates-0.1.2.dist-info/entry_points.txt
git_templates-0.1.2.dist-info/RECORD
