Metadata-Version: 2.1
Name: git-templates
Version: 0.1.2
Summary: 
License: MIT
Author: Octavio
Author-email: octavio.delser@gmail.com
Requires-Python: >=3.9,<4.0
Classifier: License :: OSI Approved :: MIT License
Classifier: Programming Language :: Python :: 3
Classifier: Programming Language :: Python :: 3.9
Classifier: Programming Language :: Python :: 3.10
Classifier: Programming Language :: Python :: 3.11
Requires-Dist: pytest (>=8.0.2,<9.0.0)
